topasgraphsim/__init__.py
topasgraphsim/__main__.py
topasgraphsim/topasgraphsim.py
topasgraphsim/src/__init__.py
topasgraphsim/src/classes/__init__.py
topasgraphsim/src/classes/eclipse_import.py
topasgraphsim/src/classes/egs_import.py
topasgraphsim/src/classes/main_viewer.py
topasgraphsim/src/classes/meas_import.py
topasgraphsim/src/classes/measurement_import.py
topasgraphsim/src/classes/menubar.py
topasgraphsim/src/classes/options.py
topasgraphsim/src/classes/paramframe.py
topasgraphsim/src/classes/profile.py
topasgraphsim/src/classes/ptw_import.py
topasgraphsim/src/classes/radcalc_import.py
topasgraphsim/src/classes/raystation_import.py
topasgraphsim/src/classes/scrollframe.py
topasgraphsim/src/classes/settings.py
topasgraphsim/src/classes/sim_import.py
topasgraphsim/src/classes/slicer_import.py
topasgraphsim/src/classes/tab.py
topasgraphsim/src/classes/tabview.py
topasgraphsim/src/classes/tgs_graph.py
topasgraphsim/src/classes/update.py
topasgraphsim/src/classes/xrange_slider.py
topasgraphsim/src/functions/__init__.py
topasgraphsim/src/functions/dp.py
topasgraphsim/src/functions/egspdd.py
topasgraphsim/src/functions/pdd.py
topasgraphsim/src/resources/add_to_context_menu.py
topasgraphsim/src/resources/info_v2.py
topasgraphsim/src/resources/language.py
topasgraphsim/src/resources/profile.json
topasgraphsim/src/resources/__pycache__/info.cpython-310.pyc
topasgraphsim/src/resources/__pycache__/info_v2.cpython-310.pyc
topasgraphsim/src/resources/__pycache__/info_v2.cpython-311.pyc
topasgraphsim/src/resources/__pycache__/info_v2.cpython-313.pyc
topasgraphsim/src/resources/__pycache__/language.cpython-310.pyc
topasgraphsim/src/resources/__pycache__/language.cpython-311.pyc
topasgraphsim/src/resources/__pycache__/language.cpython-313.pyc
topasgraphsim/src/resources/images/close.png
topasgraphsim/src/resources/images/downarrow.png
topasgraphsim/src/resources/images/gh_dark.png
topasgraphsim/src/resources/images/gh_light.png
topasgraphsim/src/resources/images/icon.ico
topasgraphsim-27.0.1.dist-info/LICENSE
topasgraphsim-27.0.1.dist-info/METADATA
topasgraphsim-27.0.1.dist-info/WHEEL
topasgraphsim-27.0.1.dist-info/entry_points.txt
topasgraphsim-27.0.1.dist-info/top_level.txt
topasgraphsim-27.0.1.dist-info/RECORD
