Metadata-Version: 2.1
Name: topasgraphsim
Version: 27.0.1
Summary: GUI to analyze the results of a Monte-Carlo radiation simulation
Home-page: https://github.com/sebasj13/TopasGraphSim
Author: Sebastian Schäfer
Author-email: sebastian.schaefer@student.uni-halle.de
Project-URL: Bug Tracker, https://github.com/sebasj13/TopasGraphSim/issues
Keywords: topas,monte-carlo,python,simulation
Classifier: Programming Language :: Python :: 3
Classifier: License :: OSI Approved :: MIT License
Classifier: Operating System :: OS Independent
Requires-Python: >=3.10
License-File: LICENSE
Requires-Dist: customtkinter
Requires-Dist: requests
Requires-Dist: numpy
Requires-Dist: scipy
Requires-Dist: pynput
Requires-Dist: opencv-python
Requires-Dist: Pillow
Requires-Dist: matplotlib
Requires-Dist: topas2numpy
Requires-Dist: pymedphys
Requires-Dist: python-tkdnd
